{
    "initialData":[
    {
        "letter":"",
        "isRightLetterAndRightPosition":false,
        "isRightLetterAndWrongPosition":false,
        "isWrongLetter":false
    },
    {
        "letter":"",
        "isRightLetterAndRightPosition":false,
        "isRightLetterAndWrongPosition":false,
        "isWrongLetter":false
    },
    {
        "letter":"",
        "isRightLetterAndRightPosition":false,
        "isRightLetterAndWrongPosition":false,
        "isWrongLetter":false
    },
    {
        "letter":"",
        "isRightLetterAndRightPosition":false,
        "isRightLetterAndWrongPosition":false,
        "isWrongLetter":false
    },
    {
        "letter":"",
        "isRightLetterAndRightPosition":false,
        "isRightLetterAndWrongPosition":false,
        "isWrongLetter":false
    }
    ]

}
